pla_analysis/__init__.py
pla_analysis/body3d.py
pla_analysis/tensile.py
pla_analysis-0.1.4.dist-info/licenses/LICENSE
pla_analysis-0.1.4.dist-info/METADATA
pla_analysis-0.1.4.dist-info/WHEEL
pla_analysis-0.1.4.dist-info/top_level.txt
pla_analysis-0.1.4.dist-info/RECORD
