Metadata-Version: 2.4
Name: pla_analysis
Version: 0.1.4
Summary: A computer vision library for automated analysis of tensile and flexion mechanical tests.
Author-email: Haritz Aseguinolaza <haritz.aseguinolaza@alumni.mondragon.edu>, Aimar Seco <aimar.seco@alumni.mondragon.edu>, Aratz Zabala <aratz.zabala@alumni.mondragon.edu>, Aitor Otzerin <aitor.otzerin@alumni.mondragon.edu>
License: MIT License
Keywords: computer-vision,mechanical-engineering,tensile-test,flexion-test,optical-tracking,displacement-measurement,opencv,material-science,extensometer,automation
Classifier: Programming Language :: Python :: 3
Classifier: License :: OSI Approved :: MIT License
Classifier: Operating System :: OS Independent
Requires-Python: >=3.7
License-File: LICENSE
Requires-Dist: opencv-python
Requires-Dist: numpy
Requires-Dist: matplotlib
Dynamic: license-file
